pypro/__init__.py
pypro/constants.py
pypro/core.py
pypro/licenses.py
pypro/main.py
pypro/utils.py
pypro/templates/Base.ipynb.j2
pypro/templates/Base_General.ipynb.j2
pypro/templates/Base_Kaggle.ipynb.j2
pypro/templates/README.md.j2
pypro/templates/__init__.py.j2
pypro/templates/config.py.j2
pypro/templates/config.yaml.j2
pypro/templates/data_loader.py.j2
pypro/templates/main.py.j2
pypro/templates/pyproject.toml.j2
kpihx_pypro-0.7.0.dist-info/METADATA
kpihx_pypro-0.7.0.dist-info/WHEEL
kpihx_pypro-0.7.0.dist-info/entry_points.txt
kpihx_pypro-0.7.0.dist-info/licenses/LICENSE
kpihx_pypro-0.7.0.dist-info/RECORD
