Metadata-Version: 2.4
Name: kpihx-pypro
Version: 0.7.0
Summary: Professional Python Project Initializer with uv, ml/dl support, and embedded config.
Author-email: Ivann KAMDEM <kapoivha@gmail.com>
License: MIT
License-File: LICENSE
Keywords: data-science,machine-learning,project-template,python,uv
Classifier: Development Status :: 4 - Beta
Classifier: Intended Audience :: Developers
Classifier: Topic :: Software Development :: Build Tools
Requires-Python: >=3.11
Requires-Dist: gitpython>=3.1.46
Requires-Dist: jinja2>=3.1.6
Requires-Dist: rich>=14.2.0
Requires-Dist: typer>=0.21.1
